{
  "started_at": 1774874999.344261,
  "ended_at": 1774875100.423756,
  "total_steps": 1945,
  "best_eval_reward": -149.3072,
  "best_eval_score": [
    0.2,
    -10.4,
    -149.3072
  ],
  "best_eval_stats": {
    "curr_avg_reward": -130.96760000000006,
    "curr_win_rate": 0.5,
    "curr_avg_score_gap": -1.15,
    "hard_avg_reward": -149.3072,
    "hard_win_rate": 0.2,
    "hard_avg_score_gap": -10.4
  },
  "history": [
    {
      "episode": 1,
      "steps": 106,
      "reward": -112.81199999999998,
      "loss": 0.0,
      "epsilon": 0.9966433333333333,
      "player_score": 15,
      "ai_score": 6,
      "player_lines": 0,
      "ai_lines": 0,
      "opp_interval": 299,
      "opp_mistake": 0.3984
    },
    {
      "episode": 2,
      "steps": 72,
      "reward": -108.184,
      "loss": 0.0,
      "epsilon": 0.9943633333333334,
      "player_score": 15,
      "ai_score": 5,
      "player_lines": 0,
      "ai_lines": 0,
      "opp_interval": 298,
      "opp_mistake": 0.3968
    },
    {
      "episode": 3,
      "steps": 84,
      "reward": -106.568,
      "loss": 0.0,
      "epsilon": 0.9917033333333334,
      "player_score": 17,
      "ai_score": 5,
      "player_lines": 0,
      "ai_lines": 0,
      "opp_interval": 297,
      "opp_mistake": 0.3951
    },
    {
      "episode": 4,
      "steps": 80,
      "reward": -115.96,
      "loss": 0.0,
      "epsilon": 0.98917,
      "player_score": 12,
      "ai_score": 6,
      "player_lines": 0,
      "ai_lines": 0,
      "opp_interval": 296,
      "opp_mistake": 0.3935
    },
    {
      "episode": 5,
      "steps": 163,
      "reward": -110.84599999999998,
      "loss": 0.0,
      "epsilon": 0.9840083333333334,
      "player_score": 19,
      "ai_score": 9,
      "player_lines": 0,
      "ai_lines": 1,
      "opp_interval": 295,
      "opp_mistake": 0.3919
    },
    {
      "episode": 6,
      "steps": 132,
      "reward": -108.20400000000002,
      "loss": 0.0,
      "epsilon": 0.9798283333333333,
      "player_score": 20,
      "ai_score": 8,
      "player_lines": 0,
      "ai_lines": 0,
      "opp_interval": 294,
      "opp_mistake": 0.3903
    },
    {
      "episode": 7,
      "steps": 78,
      "reward": -107.59600000000002,
      "loss": 0.0,
      "epsilon": 0.9773583333333333,
      "player_score": 15,
      "ai_score": 3,
      "player_lines": 0,
      "ai_lines": 0,
      "opp_interval": 293,
      "opp_mistake": 0.3886
    },
    {
      "episode": 8,
      "steps": 59,
      "reward": -107.858,
      "loss": 0.0,
      "epsilon": 0.97549,
      "player_score": 13,
      "ai_score": 3,
      "player_lines": 0,
      "ai_lines": 0,
      "opp_interval": 292,
      "opp_mistake": 0.387
    },
    {
      "episode": 9,
      "steps": 84,
      "reward": -110.208,
      "loss": 0.0,
      "epsilon": 0.97283,
      "player_score": 13,
      "ai_score": 3,
      "player_lines": 0,
      "ai_lines": 0,
      "opp_interval": 291,
      "opp_mistake": 0.3854
    },
    {
      "episode": 10,
      "steps": 78,
      "reward": -109.496,
      "loss": 0.0,
      "epsilon": 0.97036,
      "player_score": 14,
      "ai_score": 5,
      "player_lines": 0,
      "ai_lines": 0,
      "opp_interval": 290,
      "opp_mistake": 0.3838
    },
    {
      "episode": 11,
      "steps": 72,
      "reward": -111.744,
      "loss": 0.0,
      "epsilon": 0.96808,
      "player_score": 14,
      "ai_score": 4,
      "player_lines": 0,
      "ai_lines": 0,
      "opp_interval": 289,
      "opp_mistake": 0.3821
    },
    {
      "episode": 12,
      "steps": 204,
      "reward": -116.90799999999999,
      "loss": 1.1501792313960881,
      "epsilon": 0.96162,
      "player_score": 21,
      "ai_score": 12,
      "player_lines": 0,
      "ai_lines": 1,
      "opp_interval": 288,
      "opp_mistake": 0.3805
    },
    {
      "episode": 13,
      "steps": 83,
      "reward": -113.166,
      "loss": 1.313450828015086,
      "epsilon": 0.9589916666666667,
      "player_score": 15,
      "ai_score": 5,
      "player_lines": 0,
      "ai_lines": 0,
      "opp_interval": 287,
      "opp_mistake": 0.3789
    },
    {
      "episode": 14,
      "steps": 75,
      "reward": -105.08999999999999,
      "loss": 1.2840819986909628,
      "epsilon": 0.9566166666666667,
      "player_score": 16,
      "ai_score": 3,
      "player_lines": 0,
      "ai_lines": 0,
      "opp_interval": 286,
      "opp_mistake": 0.3773
    },
    {
      "episode": 15,
      "steps": 105,
      "reward": -105.05000000000001,
      "loss": 1.1806359059399083,
      "epsilon": 0.9532916666666666,
      "player_score": 18,
      "ai_score": 6,
      "player_lines": 0,
      "ai_lines": 0,
      "opp_interval": 285,
      "opp_mistake": 0.3756
    },
    {
      "episode": 16,
      "steps": 73,
      "reward": -113.38599999999998,
      "loss": 0.9310600251367648,
      "epsilon": 0.95098,
      "player_score": 13,
      "ai_score": 5,
      "player_lines": 0,
      "ai_lines": 0,
      "opp_interval": 284,
      "opp_mistake": 0.374
    },
    {
      "episode": 17,
      "steps": 56,
      "reward": -109.512,
      "loss": 1.2081793852017395,
      "epsilon": 0.9492066666666666,
      "player_score": 14,
      "ai_score": 4,
      "player_lines": 0,
      "ai_lines": 0,
      "opp_interval": 283,
      "opp_mistake": 0.3724
    },
    {
      "episode": 18,
      "steps": 97,
      "reward": -108.03400000000002,
      "loss": 0.7428543580907214,
      "epsilon": 0.946135,
      "player_score": 17,
      "ai_score": 5,
      "player_lines": 0,
      "ai_lines": 0,
      "opp_interval": 282,
      "opp_mistake": 0.3708
    },
    {
      "episode": 19,
      "steps": 105,
      "reward": -107.55,
      "loss": 0.8276070483383678,
      "epsilon": 0.94281,
      "player_score": 17,
      "ai_score": 6,
      "player_lines": 0,
      "ai_lines": 0,
      "opp_interval": 281,
      "opp_mistake": 0.3691
    },
    {
      "episode": 20,
      "steps": 78,
      "reward": -109.79599999999999,
      "loss": 0.5587950413807844,
      "epsilon": 0.94034,
      "player_score": 15,
      "ai_score": 5,
      "player_lines": 0,
      "ai_lines": 0,
      "opp_interval": 280,
      "opp_mistake": 0.3675
    },
    {
      "episode": 21,
      "steps": 61,
      "reward": -109.02200000000002,
      "loss": 0.49390824920818455,
      "epsilon": 0.9384083333333333,
      "player_score": 15,
      "ai_score": 4,
      "player_lines": 0,
      "ai_lines": 0,
      "opp_interval": 279,
      "opp_mistake": 0.3659
    }
  ]
}